tolerant_isinstance/LICENSE
tolerant_isinstance/README.MD
tolerant_isinstance/__init__.py
tolerant_isinstance/requirements.txt
tolerant_isinstance/thirdparty.json
tolerant_isinstance-0.10.dist-info/LICENSE.rst
tolerant_isinstance-0.10.dist-info/METADATA
tolerant_isinstance-0.10.dist-info/WHEEL
tolerant_isinstance-0.10.dist-info/top_level.txt
tolerant_isinstance-0.10.dist-info/RECORD
